pyTraffMonetizer/__init__.py
pyTraffMonetizer/exceptions.py
pyTraffMonetizer/traffmonetizer.py
pyTraffMonetizer-0.0.1.dist-info/LICENSE
pyTraffMonetizer-0.0.1.dist-info/METADATA
pyTraffMonetizer-0.0.1.dist-info/WHEEL
pyTraffMonetizer-0.0.1.dist-info/top_level.txt
pyTraffMonetizer-0.0.1.dist-info/RECORD
