Metadata-Version: 2.1
Name: pyTraffMonetizer
Version: 0.0.1
Summary: UNOFFICIAL Python bindings for TraffMonetizer Dashboard API
Home-page: https://github.com/coder-amogh/pyTraffMonetizer
Author: coder-amogh (Amogh Datar)
License: UNKNOWN
Project-URL: Bug Tracker, https://github.com/coder-amogh/pyTraffMonetizer/issues
Keywords: python,traffmonetizer,traff,passive income,traffmonetizer api,traffmonetizer dashboard,python traffmonetizer,traff mon
Platform: UNKNOWN
Classifier: Development Status :: 5 - Production/Stable
Classifier: Intended Audience :: Developers
Classifier: Programming Language :: Python :: 3
Classifier: Operating System :: OS Independent
Requires-Dist: requests
Requires-Dist: pySocks
